bibmon/__init__.py
bibmon/_alarms.py
bibmon/_autoencoder.py
bibmon/_bibmon_tools.py
bibmon/_esn.py
bibmon/_generic_model.py
bibmon/_load_data.py
bibmon/_pca.py
bibmon/_preprocess.py
bibmon/_sbm.py
bibmon/_sklearn_manifold.py
bibmon/_sklearn_regressor.py
bibmon/_template_generic_model_childs.py
bibmon/real_process_data/__init__.py
bibmon/real_process_data/real_process_data.csv
bibmon/tennessee_eastman/__init__.py
bibmon/tennessee_eastman/d00.dat
bibmon/tennessee_eastman/d00_te.dat
bibmon/tennessee_eastman/d01.dat
bibmon/tennessee_eastman/d01_te.dat
bibmon/tennessee_eastman/d02.dat
bibmon/tennessee_eastman/d02_te.dat
bibmon/tennessee_eastman/d03.dat
bibmon/tennessee_eastman/d03_te.dat
bibmon/tennessee_eastman/d04.dat
bibmon/tennessee_eastman/d04_te.dat
bibmon/tennessee_eastman/d05.dat
bibmon/tennessee_eastman/d05_te.dat
bibmon/tennessee_eastman/d06.dat
bibmon/tennessee_eastman/d06_te.dat
bibmon/tennessee_eastman/d07.dat
bibmon/tennessee_eastman/d07_te.dat
bibmon/tennessee_eastman/d08.dat
bibmon/tennessee_eastman/d08_te.dat
bibmon/tennessee_eastman/d09.dat
bibmon/tennessee_eastman/d09_te.dat
bibmon/tennessee_eastman/d10.dat
bibmon/tennessee_eastman/d10_te.dat
bibmon/tennessee_eastman/d11.dat
bibmon/tennessee_eastman/d11_te.dat
bibmon/tennessee_eastman/d12.dat
bibmon/tennessee_eastman/d12_te.dat
bibmon/tennessee_eastman/d13.dat
bibmon/tennessee_eastman/d13_te.dat
bibmon/tennessee_eastman/d14.dat
bibmon/tennessee_eastman/d14_te.dat
bibmon/tennessee_eastman/d15.dat
bibmon/tennessee_eastman/d15_te.dat
bibmon/tennessee_eastman/d16.dat
bibmon/tennessee_eastman/d16_te.dat
bibmon/tennessee_eastman/d17.dat
bibmon/tennessee_eastman/d17_te.dat
bibmon/tennessee_eastman/d18.dat
bibmon/tennessee_eastman/d18_te.dat
bibmon/tennessee_eastman/d19.dat
bibmon/tennessee_eastman/d19_te.dat
bibmon/tennessee_eastman/d20.dat
bibmon/tennessee_eastman/d20_te.dat
bibmon/tennessee_eastman/d21.dat
bibmon/tennessee_eastman/d21_te.dat
bibmon-1.2.0.dist-info/LICENSE.md
bibmon-1.2.0.dist-info/METADATA
bibmon-1.2.0.dist-info/WHEEL
bibmon-1.2.0.dist-info/top_level.txt
bibmon-1.2.0.dist-info/RECORD
