Metadata-Version: 2.2
Name: bibmon
Version: 1.2.0
Summary: Library with routines for data-driven process monitoring.
Home-page: https://github.com/petrobras/bibmon
Author: BibMon developers
Author-email: cc-bibmon@petrobras.com.br
License: Apache 2.0
Requires-Python: >=3.10
License-File: LICENSE.md
Requires-Dist: numpy>=1.26
Requires-Dist: scipy>=1.10
Requires-Dist: scikit-learn>=1.5.1
Requires-Dist: pandas>=2.2.2
Requires-Dist: matplotlib>=3.9.0
Requires-Dist: seaborn>=0.13.2
Requires-Dist: statsmodels>=0.14.1
Requires-Dist: optuna>=3.6.1
Dynamic: author
Dynamic: author-email
Dynamic: description
Dynamic: description-content-type
Dynamic: home-page
Dynamic: license
Dynamic: requires-dist
Dynamic: requires-python
Dynamic: summary
